[{"epoch": 1, "Training Loss": 0.15661502184216367, "Validation Loss": 0.27895096730854774, "Training Time": "0:00:01", "Validation Time": "0:00:00"}, {"epoch": 2, "Training Loss": 0.0835127989913142, "Validation Loss": 0.27519467790369634, "Training Time": "0:00:01", "Validation Time": "0:00:00"}, {"epoch": 3, "Training Loss": 0.07697630153838979, "Validation Loss": 0.24513591039511892, "Training Time": "0:00:01", "Validation Time": "0:00:00"}, {"epoch": 4, "Training Loss": 0.07090839942873911, "Validation Loss": 0.21226527210738924, "Training Time": "0:00:01", "Validation Time": "0:00:00"}, {"epoch": 5, "Training Loss": 0.07073250125313914, "Validation Loss": 0.19560860870061098, "Training Time": "0:00:01", "Validation Time": "0:00:00"}, {"epoch": 6, "Training Loss": 0.06779742844749329, "Validation Loss": 0.18540070261116381, "Training Time": "0:00:01", "Validation Time": "0:00:00"}, {"epoch": 7, "Training Loss": 0.0687282764677738, "Validation Loss": 0.172446605645948, "Training Time": "0:00:01", "Validation Time": "0:00:00"}, {"epoch": 8, "Training Loss": 0.06693991910406323, "Validation Loss": 0.1562872920875196, "Training Time": "0:00:01", "Validation Time": "0:00:00"}, {"epoch": 9, "Training Loss": 0.0638821866623191, "Validation Loss": 0.15186598634830228, "Training Time": "0:00:01", "Validation Time": "0:00:00"}, {"epoch": 10, "Training Loss": 0.0638601256101284, "Validation Loss": 0.1263820348928372, "Training Time": "0:00:01", "Validation Time": "0:00:00"}, {"epoch": 11, "Training Loss": 0.06530456234549367, "Validation Loss": 0.13427442484707744, "Training Time": "0:00:01", "Validation Time": "0:00:00"}, {"epoch": 12, "Training Loss": 0.05969283218647158, "Validation Loss": 0.13929126246107948, "Training Time": "0:00:01", "Validation Time": "0:00:00"}, {"epoch": 13, "Training Loss": 0.06011722988860552, "Validation Loss": 0.1259359988487429, "Training Time": "0:00:01", "Validation Time": "0:00:00"}, {"epoch": 14, "Training Loss": 0.060976423117397135, "Validation Loss": 0.13068372404409778, "Training Time": "0:00:01", "Validation Time": "0:00:00"}, {"epoch": 15, "Training Loss": 0.06022824366945167, "Validation Loss": 0.13930397798065786, "Training Time": "0:00:01", "Validation Time": "0:00:00"}, {"epoch": 16, "Training Loss": 0.05968374952587278, "Validation Loss": 0.1258490289113036, "Training Time": "0:00:01", "Validation Time": "0:00:00"}, {"epoch": 17, "Training Loss": 0.06072598673229994, "Validation Loss": 0.12395082696996353, "Training Time": "0:00:01", "Validation Time": "0:00:00"}, {"epoch": 18, "Training Loss": 0.05892556351717822, "Validation Loss": 0.12449597995038386, "Training Time": "0:00:01", "Validation Time": "0:00:00"}, {"epoch": 19, "Training Loss": 0.058863517784968365, "Validation Loss": 0.11439053403834502, "Training Time": "0:00:01", "Validation Time": "0:00:00"}, {"epoch": 20, "Training Loss": 0.06063312947923361, "Validation Loss": 0.13167829770180914, "Training Time": "0:00:01", "Validation Time": "0:00:00"}, {"epoch": 21, "Training Loss": 0.059647962403332075, "Validation Loss": 0.13609312529917117, "Training Time": "0:00:01", "Validation Time": "0:00:00"}, {"epoch": 22, "Training Loss": 0.06022944192423724, "Validation Loss": 0.12401690768698852, "Training Time": "0:00:01", "Validation Time": "0:00:00"}, {"epoch": 23, "Training Loss": 0.05762419511325831, "Validation Loss": 0.116376678838774, "Training Time": "0:00:01", "Validation Time": "0:00:00"}, {"epoch": 24, "Training Loss": 0.05674079894413089, "Validation Loss": 0.13102456520277042, "Training Time": "0:00:01", "Validation Time": "0:00:00"}, {"epoch": 25, "Training Loss": 0.057814621292921, "Validation Loss": 0.13255137115440987, "Training Time": "0:00:01", "Validation Time": "0:00:00"}, {"epoch": 26, "Training Loss": 0.05693790991032539, "Validation Loss": 0.11970933857891294, "Training Time": "0:00:01", "Validation Time": "0:00:00"}, {"epoch": 27, "Training Loss": 0.05627860060004994, "Validation Loss": 0.12807949763481263, "Training Time": "0:00:01", "Validation Time": "0:00:00"}, {"epoch": 28, "Training Loss": 0.055935833802403405, "Validation Loss": 0.11126290103075681, "Training Time": "0:00:01", "Validation Time": "0:00:00"}, {"epoch": 29, "Training Loss": 0.0576394260059609, "Validation Loss": 0.12149394027612827, "Training Time": "0:00:01", "Validation Time": "0:00:00"}, {"epoch": 30, "Training Loss": 0.05673971028435369, "Validation Loss": 0.13736566370008169, "Training Time": "0:00:01", "Validation Time": "0:00:00"}, {"epoch": 31, "Training Loss": 0.05688835403687039, "Validation Loss": 0.12715862891464322, "Training Time": "0:00:01", "Validation Time": "0:00:00"}, {"epoch": 32, "Training Loss": 0.05538453601820524, "Validation Loss": 0.11729160013298194, "Training Time": "0:00:01", "Validation Time": "0:00:00"}, {"epoch": 33, "Training Loss": 0.05600318755781235, "Validation Loss": 0.1235974293064188, "Training Time": "0:00:01", "Validation Time": "0:00:00"}, {"epoch": 34, "Training Loss": 0.05595265739532404, "Validation Loss": 0.1219257975893992, "Training Time": "0:00:01", "Validation Time": "0:00:00"}, {"epoch": 35, "Training Loss": 0.05582543400137924, "Validation Loss": 0.11612442370366167, "Training Time": "0:00:01", "Validation Time": "0:00:00"}, {"epoch": 36, "Training Loss": 0.05608139298856259, "Validation Loss": 0.11101429964657183, "Training Time": "0:00:01", "Validation Time": "0:00:00"}, {"epoch": 37, "Training Loss": 0.05350616871877465, "Validation Loss": 0.11412280439226716, "Training Time": "0:00:01", "Validation Time": "0:00:00"}, {"epoch": 38, "Training Loss": 0.056919346199652485, "Validation Loss": 0.11897256411612034, "Training Time": "0:00:01", "Validation Time": "0:00:00"}, {"epoch": 39, "Training Loss": 0.05503864702443744, "Validation Loss": 0.1078740544617176, "Training Time": "0:00:01", "Validation Time": "0:00:00"}, {"epoch": 40, "Training Loss": 0.05241859170153391, "Validation Loss": 0.11196536639774288, "Training Time": "0:00:01", "Validation Time": "0:00:00"}, {"epoch": 41, "Training Loss": 0.05387683565793342, "Validation Loss": 0.10836377939968198, "Training Time": "0:00:01", "Validation Time": "0:00:00"}, {"epoch": 42, "Training Loss": 0.05509466275486142, "Validation Loss": 0.10562722895432401, "Training Time": "0:00:01", "Validation Time": "0:00:00"}, {"epoch": 43, "Training Loss": 0.05559949397954137, "Validation Loss": 0.11544431987460013, "Training Time": "0:00:01", "Validation Time": "0:00:00"}, {"epoch": 44, "Training Loss": 0.05384363932318466, "Validation Loss": 0.10931369000011021, "Training Time": "0:00:01", "Validation Time": "0:00:00"}, {"epoch": 45, "Training Loss": 0.05316858010496511, "Validation Loss": 0.11015778145304432, "Training Time": "0:00:01", "Validation Time": "0:00:00"}, {"epoch": 46, "Training Loss": 0.051763526822418665, "Validation Loss": 0.12642516181976707, "Training Time": "0:00:01", "Validation Time": "0:00:00"}, {"epoch": 47, "Training Loss": 0.051899338331679964, "Validation Loss": 0.11007732097749356, "Training Time": "0:00:01", "Validation Time": "0:00:00"}, {"epoch": 48, "Training Loss": 0.05098370480416126, "Validation Loss": 0.1174976771214494, "Training Time": "0:00:01", "Validation Time": "0:00:00"}, {"epoch": 49, "Training Loss": 0.05557302603887957, "Validation Loss": 0.11017745139974135, "Training Time": "0:00:01", "Validation Time": "0:00:00"}, {"epoch": 50, "Training Loss": 0.05622505741193891, "Validation Loss": 0.12517077503380952, "Training Time": "0:00:01", "Validation Time": "0:00:00"}, {"epoch": 51, "Training Loss": 0.051294852191105834, "Validation Loss": 0.11157225244851024, "Training Time": "0:00:01", "Validation Time": "0:00:00"}, {"epoch": 52, "Training Loss": 0.0544984481968852, "Validation Loss": 0.10383273281708912, "Training Time": "0:00:01", "Validation Time": "0:00:00"}, {"epoch": 53, "Training Loss": 0.05209901937131965, "Validation Loss": 0.10583065622658641, "Training Time": "0:00:01", "Validation Time": "0:00:00"}, {"epoch": 54, "Training Loss": 0.053801504778134265, "Validation Loss": 0.11031861913700898, "Training Time": "0:00:01", "Validation Time": "0:00:00"}, {"epoch": 55, "Training Loss": 0.05440640836997434, "Validation Loss": 0.11836818191740248, "Training Time": "0:00:01", "Validation Time": "0:00:00"}, {"epoch": 56, "Training Loss": 0.052727601965239575, "Validation Loss": 0.11610695492062303, "Training Time": "0:00:01", "Validation Time": "0:00:00"}, {"epoch": 57, "Training Loss": 0.0490955826284927, "Validation Loss": 0.10677800824244817, "Training Time": "0:00:01", "Validation Time": "0:00:00"}, {"epoch": 58, "Training Loss": 0.04973578043282032, "Validation Loss": 0.1037982660173266, "Training Time": "0:00:01", "Validation Time": "0:00:00"}, {"epoch": 59, "Training Loss": 0.05434451158223457, "Validation Loss": 0.11156997401957158, "Training Time": "0:00:01", "Validation Time": "0:00:00"}, {"epoch": 60, "Training Loss": 0.04950077375397086, "Validation Loss": 0.10156029842242047, "Training Time": "0:00:01", "Validation Time": "0:00:00"}, {"epoch": 61, "Training Loss": 0.05041213290722564, "Validation Loss": 0.11100655801042363, "Training Time": "0:00:01", "Validation Time": "0:00:00"}, {"epoch": 62, "Training Loss": 0.050504217634713924, "Validation Loss": 0.10887196508270723, "Training Time": "0:00:01", "Validation Time": "0:00:00"}, {"epoch": 63, "Training Loss": 0.05119278833140121, "Validation Loss": 0.10237819322005466, "Training Time": "0:00:01", "Validation Time": "0:00:00"}, {"epoch": 64, "Training Loss": 0.050581654130892696, "Validation Loss": 0.10135031836452307, "Training Time": "0:00:01", "Validation Time": "0:00:00"}, {"epoch": 65, "Training Loss": 0.050605609094680745, "Validation Loss": 0.09254973885361795, "Training Time": "0:00:01", "Validation Time": "0:00:00"}, {"epoch": 66, "Training Loss": 0.04984463582595074, "Validation Loss": 0.10578423503924299, "Training Time": "0:00:01", "Validation Time": "0:00:00"}, {"epoch": 67, "Training Loss": 0.05068256881001384, "Validation Loss": 0.10379276196989748, "Training Time": "0:00:01", "Validation Time": "0:00:00"}, {"epoch": 68, "Training Loss": 0.04827155620726042, "Validation Loss": 0.09892957133275491, "Training Time": "0:00:01", "Validation Time": "0:00:00"}, {"epoch": 69, "Training Loss": 0.05134757410648257, "Validation Loss": 0.10656291894890645, "Training Time": "0:00:01", "Validation Time": "0:00:00"}, {"epoch": 70, "Training Loss": 0.04750688060858222, "Validation Loss": 0.09729602891537878, "Training Time": "0:00:01", "Validation Time": "0:00:00"}, {"epoch": 71, "Training Loss": 0.050549084545914516, "Validation Loss": 0.09995863855712944, "Training Time": "0:00:01", "Validation Time": "0:00:00"}, {"epoch": 72, "Training Loss": 0.04672008139449497, "Validation Loss": 0.10310168171094523, "Training Time": "0:00:01", "Validation Time": "0:00:00"}, {"epoch": 73, "Training Loss": 0.04824644690162914, "Validation Loss": 0.10318449470731947, "Training Time": "0:00:01", "Validation Time": "0:00:00"}, {"epoch": 74, "Training Loss": 0.05003928373632736, "Validation Loss": 0.10721931916972001, "Training Time": "0:00:01", "Validation Time": "0:00:00"}, {"epoch": 75, "Training Loss": 0.0518689623990551, "Validation Loss": 0.10113049491688057, "Training Time": "0:00:01", "Validation Time": "0:00:00"}, {"epoch": 76, "Training Loss": 0.0511186538610694, "Validation Loss": 0.0912420852454724, "Training Time": "0:00:01", "Validation Time": "0:00:00"}, {"epoch": 77, "Training Loss": 0.0499824455311132, "Validation Loss": 0.09958191326370945, "Training Time": "0:00:01", "Validation Time": "0:00:00"}, {"epoch": 78, "Training Loss": 0.04974248739349288, "Validation Loss": 0.10669448771686466, "Training Time": "0:00:01", "Validation Time": "0:00:00"}, {"epoch": 79, "Training Loss": 0.05120240315405089, "Validation Loss": 0.10195000442089858, "Training Time": "0:00:01", "Validation Time": "0:00:00"}, {"epoch": 80, "Training Loss": 0.04755021655325626, "Validation Loss": 0.10356229688558313, "Training Time": "0:00:01", "Validation Time": "0:00:00"}, {"epoch": 81, "Training Loss": 0.05069719885237688, "Validation Loss": 0.09747417940309754, "Training Time": "0:00:01", "Validation Time": "0:00:00"}, {"epoch": 82, "Training Loss": 0.04817563944257969, "Validation Loss": 0.09366915644043022, "Training Time": "0:00:01", "Validation Time": "0:00:00"}, {"epoch": 83, "Training Loss": 0.049705676925043726, "Validation Loss": 0.10917186550796032, "Training Time": "0:00:01", "Validation Time": "0:00:00"}, {"epoch": 84, "Training Loss": 0.04818963292379712, "Validation Loss": 0.11093435298513483, "Training Time": "0:00:01", "Validation Time": "0:00:00"}, {"epoch": 85, "Training Loss": 0.048490618368567426, "Validation Loss": 0.10607779039828866, "Training Time": "0:00:01", "Validation Time": "0:00:00"}, {"epoch": 86, "Training Loss": 0.050283377509304256, "Validation Loss": 0.10273556266393927, "Training Time": "0:00:01", "Validation Time": "0:00:00"}, {"epoch": 87, "Training Loss": 0.046201009078081265, "Validation Loss": 0.10575081373530405, "Training Time": "0:00:01", "Validation Time": "0:00:00"}, {"epoch": 88, "Training Loss": 0.04772068201022786, "Validation Loss": 0.10185041430371779, "Training Time": "0:00:01", "Validation Time": "0:00:00"}, {"epoch": 89, "Training Loss": 0.049530396814089876, "Validation Loss": 0.10687923969493972, "Training Time": "0:00:01", "Validation Time": "0:00:00"}, {"epoch": 90, "Training Loss": 0.045816606976265134, "Validation Loss": 0.10223479430984568, "Training Time": "0:00:01", "Validation Time": "0:00:00"}, {"epoch": 91, "Training Loss": 0.047195702871351046, "Validation Loss": 0.10691520675188965, "Training Time": "0:00:01", "Validation Time": "0:00:00"}, {"epoch": 92, "Training Loss": 0.047333959648169055, "Validation Loss": 0.10148363739803985, "Training Time": "0:00:01", "Validation Time": "0:00:00"}, {"epoch": 93, "Training Loss": 0.0435369408256266, "Validation Loss": 0.09729209832019275, "Training Time": "0:00:01", "Validation Time": "0:00:00"}, {"epoch": 94, "Training Loss": 0.048328571246806964, "Validation Loss": 0.09470167976838571, "Training Time": "0:00:01", "Validation Time": "0:00:00"}, {"epoch": 95, "Training Loss": 0.0478613248311503, "Validation Loss": 0.0954178826952422, "Training Time": "0:00:01", "Validation Time": "0:00:00"}, {"epoch": 96, "Training Loss": 0.050200760867013486, "Validation Loss": 0.09723660998322346, "Training Time": "0:00:01", "Validation Time": "0:00:00"}, {"epoch": 97, "Training Loss": 0.045727906774642856, "Validation Loss": 0.10276269836834183, "Training Time": "0:00:01", "Validation Time": "0:00:00"}, {"epoch": 98, "Training Loss": 0.048518188518666946, "Validation Loss": 0.099897144086383, "Training Time": "0:00:01", "Validation Time": "0:00:00"}, {"epoch": 99, "Training Loss": 0.047399611745116324, "Validation Loss": 0.10144959300480506, "Training Time": "0:00:01", "Validation Time": "0:00:00"}, {"epoch": 100, "Training Loss": 0.04451099369934825, "Validation Loss": 0.09850270004460106, "Training Time": "0:00:01", "Validation Time": "0:00:00"}]