[{"epoch": 1, "Training Loss": 0.18019982494933662, "Validation Loss": 0.24248642929726177, "Training Time": "0:00:01", "Validation Time": "0:00:00"}, {"epoch": 2, "Training Loss": 0.08455165135132713, "Validation Loss": 0.2143573180116989, "Training Time": "0:00:01", "Validation Time": "0:00:00"}, {"epoch": 3, "Training Loss": 0.07623380834973136, "Validation Loss": 0.21222341502154315, "Training Time": "0:00:01", "Validation Time": "0:00:00"}, {"epoch": 4, "Training Loss": 0.07211748201313407, "Validation Loss": 0.21363049483409635, "Training Time": "0:00:01", "Validation Time": "0:00:00"}, {"epoch": 5, "Training Loss": 0.07136857835359352, "Validation Loss": 0.21873958753766837, "Training Time": "0:00:01", "Validation Time": "0:00:00"}, {"epoch": 6, "Training Loss": 0.06956616718928481, "Validation Loss": 0.20864154315657085, "Training Time": "0:00:01", "Validation Time": "0:00:00"}, {"epoch": 7, "Training Loss": 0.06519550093731215, "Validation Loss": 0.18734583465589416, "Training Time": "0:00:01", "Validation Time": "0:00:00"}, {"epoch": 8, "Training Loss": 0.06796206495789595, "Validation Loss": 0.17490356318928577, "Training Time": "0:00:01", "Validation Time": "0:00:00"}, {"epoch": 9, "Training Loss": 0.06563715343038704, "Validation Loss": 0.18488944804778806, "Training Time": "0:00:01", "Validation Time": "0:00:00"}, {"epoch": 10, "Training Loss": 0.0680558860388606, "Validation Loss": 0.1681622657235022, "Training Time": "0:00:01", "Validation Time": "0:00:00"}, {"epoch": 11, "Training Loss": 0.06676447906119878, "Validation Loss": 0.15838992043777747, "Training Time": "0:00:01", "Validation Time": "0:00:00"}, {"epoch": 12, "Training Loss": 0.06448721721075303, "Validation Loss": 0.15423199617200428, "Training Time": "0:00:01", "Validation Time": "0:00:00"}, {"epoch": 13, "Training Loss": 0.06450479838044144, "Validation Loss": 0.13297838517637164, "Training Time": "0:00:01", "Validation Time": "0:00:00"}, {"epoch": 14, "Training Loss": 0.06680497415363788, "Validation Loss": 0.1339963658678311, "Training Time": "0:00:01", "Validation Time": "0:00:00"}, {"epoch": 15, "Training Loss": 0.06077025308771882, "Validation Loss": 0.14028218533429834, "Training Time": "0:00:01", "Validation Time": "0:00:00"}, {"epoch": 16, "Training Loss": 0.06134105776111747, "Validation Loss": 0.13531161313531576, "Training Time": "0:00:01", "Validation Time": "0:00:00"}, {"epoch": 17, "Training Loss": 0.06159826194607588, "Validation Loss": 0.13467500062176474, "Training Time": "0:00:01", "Validation Time": "0:00:00"}, {"epoch": 18, "Training Loss": 0.06179884898714548, "Validation Loss": 0.13886899466591854, "Training Time": "0:00:01", "Validation Time": "0:00:00"}, {"epoch": 19, "Training Loss": 0.06186245735734701, "Validation Loss": 0.12780040585332447, "Training Time": "0:00:01", "Validation Time": "0:00:00"}, {"epoch": 20, "Training Loss": 0.06270998065728088, "Validation Loss": 0.12903505798291276, "Training Time": "0:00:01", "Validation Time": "0:00:00"}, {"epoch": 21, "Training Loss": 0.0603296602491376, "Validation Loss": 0.1310297679156065, "Training Time": "0:00:01", "Validation Time": "0:00:00"}, {"epoch": 22, "Training Loss": 0.06105853391074857, "Validation Loss": 0.11803528894152907, "Training Time": "0:00:01", "Validation Time": "0:00:00"}, {"epoch": 23, "Training Loss": 0.062245078480174375, "Validation Loss": 0.15062482020369283, "Training Time": "0:00:01", "Validation Time": "0:00:00"}, {"epoch": 24, "Training Loss": 0.06214742426175711, "Validation Loss": 0.14070337762435278, "Training Time": "0:00:01", "Validation Time": "0:00:00"}, {"epoch": 25, "Training Loss": 0.06213363302481729, "Validation Loss": 0.12610470262114648, "Training Time": "0:00:01", "Validation Time": "0:00:00"}, {"epoch": 26, "Training Loss": 0.05904879679166993, "Validation Loss": 0.11346505168411467, "Training Time": "0:00:01", "Validation Time": "0:00:00"}, {"epoch": 27, "Training Loss": 0.058418729489799155, "Validation Loss": 0.12805591289091994, "Training Time": "0:00:01", "Validation Time": "0:00:00"}, {"epoch": 28, "Training Loss": 0.059601490177907224, "Validation Loss": 0.12782158267994723, "Training Time": "0:00:01", "Validation Time": "0:00:00"}, {"epoch": 29, "Training Loss": 0.059082160881438923, "Validation Loss": 0.12444017972383234, "Training Time": "0:00:01", "Validation Time": "0:00:00"}, {"epoch": 30, "Training Loss": 0.05819324411798355, "Validation Loss": 0.1296723536733124, "Training Time": "0:00:01", "Validation Time": "0:00:00"}, {"epoch": 31, "Training Loss": 0.0574002891259138, "Validation Loss": 0.12062478127578895, "Training Time": "0:00:01", "Validation Time": "0:00:00"}, {"epoch": 32, "Training Loss": 0.05981665984402562, "Validation Loss": 0.12227722988636405, "Training Time": "0:00:01", "Validation Time": "0:00:00"}, {"epoch": 33, "Training Loss": 0.058226366882580656, "Validation Loss": 0.13944407035079268, "Training Time": "0:00:01", "Validation Time": "0:00:00"}, {"epoch": 34, "Training Loss": 0.05915024204309596, "Validation Loss": 0.12168524683349663, "Training Time": "0:00:01", "Validation Time": "0:00:00"}, {"epoch": 35, "Training Loss": 0.05702016947487759, "Validation Loss": 0.1221941731594227, "Training Time": "0:00:01", "Validation Time": "0:00:00"}, {"epoch": 36, "Training Loss": 0.05928342066878496, "Validation Loss": 0.12401867788974885, "Training Time": "0:00:01", "Validation Time": "0:00:00"}, {"epoch": 37, "Training Loss": 0.058337555587464986, "Validation Loss": 0.12057875186480858, "Training Time": "0:00:01", "Validation Time": "0:00:00"}, {"epoch": 38, "Training Loss": 0.057856643962305644, "Validation Loss": 0.1216630554171624, "Training Time": "0:00:01", "Validation Time": "0:00:00"}, {"epoch": 39, "Training Loss": 0.05837898483543202, "Validation Loss": 0.11472239572968748, "Training Time": "0:00:01", "Validation Time": "0:00:00"}, {"epoch": 40, "Training Loss": 0.05631212769725988, "Validation Loss": 0.12482591518373401, "Training Time": "0:00:01", "Validation Time": "0:00:00"}, {"epoch": 41, "Training Loss": 0.05965094156563282, "Validation Loss": 0.1276950793409789, "Training Time": "0:00:01", "Validation Time": "0:00:00"}, {"epoch": 42, "Training Loss": 0.05767982376869335, "Validation Loss": 0.10906751474572553, "Training Time": "0:00:01", "Validation Time": "0:00:00"}, {"epoch": 43, "Training Loss": 0.05483247629085253, "Validation Loss": 0.11430124496972119, "Training Time": "0:00:01", "Validation Time": "0:00:00"}, {"epoch": 44, "Training Loss": 0.05609132796850835, "Validation Loss": 0.11997852026036492, "Training Time": "0:00:01", "Validation Time": "0:00:00"}, {"epoch": 45, "Training Loss": 0.05791949557010517, "Validation Loss": 0.11073648419093203, "Training Time": "0:00:01", "Validation Time": "0:00:00"}, {"epoch": 46, "Training Loss": 0.058349469659286876, "Validation Loss": 0.12422024375862545, "Training Time": "0:00:01", "Validation Time": "0:00:00"}, {"epoch": 47, "Training Loss": 0.056546159838001396, "Validation Loss": 0.11584795742399162, "Training Time": "0:00:01", "Validation Time": "0:00:00"}, {"epoch": 48, "Training Loss": 0.056502861538252167, "Validation Loss": 0.11205636558157427, "Training Time": "0:00:01", "Validation Time": "0:00:00"}, {"epoch": 49, "Training Loss": 0.05448263252024041, "Validation Loss": 0.12315960704452461, "Training Time": "0:00:01", "Validation Time": "0:00:00"}, {"epoch": 50, "Training Loss": 0.054678895922247756, "Validation Loss": 0.11861691320383991, "Training Time": "0:00:01", "Validation Time": "0:00:00"}, {"epoch": 51, "Training Loss": 0.05312235138357379, "Validation Loss": 0.11823374191644015, "Training Time": "0:00:01", "Validation Time": "0:00:00"}, {"epoch": 52, "Training Loss": 0.058945529011273104, "Validation Loss": 0.1185755472354315, "Training Time": "0:00:01", "Validation Time": "0:00:00"}, {"epoch": 53, "Training Loss": 0.05986962538905615, "Validation Loss": 0.12678294214937422, "Training Time": "0:00:01", "Validation Time": "0:00:00"}, {"epoch": 54, "Training Loss": 0.05374792723721543, "Validation Loss": 0.11295110746114342, "Training Time": "0:00:01", "Validation Time": "0:00:00"}, {"epoch": 55, "Training Loss": 0.057476178331430566, "Validation Loss": 0.11179200711625593, "Training Time": "0:00:01", "Validation Time": "0:00:00"}, {"epoch": 56, "Training Loss": 0.054734448993275335, "Validation Loss": 0.11236128576651767, "Training Time": "0:00:01", "Validation Time": "0:00:00"}, {"epoch": 57, "Training Loss": 0.05639458876536336, "Validation Loss": 0.1136731871024326, "Training Time": "0:00:01", "Validation Time": "0:00:00"}, {"epoch": 58, "Training Loss": 0.05832274426749453, "Validation Loss": 0.12075244676735666, "Training Time": "0:00:01", "Validation Time": "0:00:00"}, {"epoch": 59, "Training Loss": 0.0558678766799181, "Validation Loss": 0.12349253623849815, "Training Time": "0:00:01", "Validation Time": "0:00:00"}, {"epoch": 60, "Training Loss": 0.052652920375383175, "Validation Loss": 0.11795348349820685, "Training Time": "0:00:01", "Validation Time": "0:00:00"}, {"epoch": 61, "Training Loss": 0.053370244653765546, "Validation Loss": 0.10946237958139843, "Training Time": "0:00:01", "Validation Time": "0:00:00"}, {"epoch": 62, "Training Loss": 0.05813743197034265, "Validation Loss": 0.11299555424462866, "Training Time": "0:00:01", "Validation Time": "0:00:00"}, {"epoch": 63, "Training Loss": 0.0541856913675749, "Validation Loss": 0.11341334058454743, "Training Time": "0:00:01", "Validation Time": "0:00:00"}, {"epoch": 64, "Training Loss": 0.053793675716706485, "Validation Loss": 0.11780146309347064, "Training Time": "0:00:01", "Validation Time": "0:00:00"}, {"epoch": 65, "Training Loss": 0.053673927325668724, "Validation Loss": 0.1200006434486972, "Training Time": "0:00:01", "Validation Time": "0:00:00"}, {"epoch": 66, "Training Loss": 0.056134369934714115, "Validation Loss": 0.11197227605239109, "Training Time": "0:00:01", "Validation Time": "0:00:00"}, {"epoch": 67, "Training Loss": 0.055330308377309595, "Validation Loss": 0.1087924678016592, "Training Time": "0:00:01", "Validation Time": "0:00:00"}, {"epoch": 68, "Training Loss": 0.05467223199300988, "Validation Loss": 0.10340640445550282, "Training Time": "0:00:01", "Validation Time": "0:00:00"}, {"epoch": 69, "Training Loss": 0.05380328726456609, "Validation Loss": 0.11433072829688037, "Training Time": "0:00:01", "Validation Time": "0:00:00"}, {"epoch": 70, "Training Loss": 0.05485986831143152, "Validation Loss": 0.11215786263346672, "Training Time": "0:00:01", "Validation Time": "0:00:00"}, {"epoch": 71, "Training Loss": 0.051339724779042396, "Validation Loss": 0.10624674900814339, "Training Time": "0:00:01", "Validation Time": "0:00:00"}, {"epoch": 72, "Training Loss": 0.055044506758798004, "Validation Loss": 0.11413678264728298, "Training Time": "0:00:01", "Validation Time": "0:00:00"}, {"epoch": 73, "Training Loss": 0.052567898022920584, "Validation Loss": 0.10592923561731975, "Training Time": "0:00:01", "Validation Time": "0:00:00"}, {"epoch": 74, "Training Loss": 0.053729602083737074, "Validation Loss": 0.10427229327184183, "Training Time": "0:00:01", "Validation Time": "0:00:00"}, {"epoch": 75, "Training Loss": 0.050901231724162437, "Validation Loss": 0.11686126894696995, "Training Time": "0:00:01", "Validation Time": "0:00:00"}, {"epoch": 76, "Training Loss": 0.052874113528361154, "Validation Loss": 0.11474450801809628, "Training Time": "0:00:01", "Validation Time": "0:00:00"}, {"epoch": 77, "Training Loss": 0.054750012952921, "Validation Loss": 0.11898511344635929, "Training Time": "0:00:01", "Validation Time": "0:00:00"}, {"epoch": 78, "Training Loss": 0.056301107682114424, "Validation Loss": 0.10906241220180635, "Training Time": "0:00:01", "Validation Time": "0:00:00"}, {"epoch": 79, "Training Loss": 0.056082324553714244, "Validation Loss": 0.10089880676457176, "Training Time": "0:00:01", "Validation Time": "0:00:00"}, {"epoch": 80, "Training Loss": 0.054473145990524184, "Validation Loss": 0.10470936054156886, "Training Time": "0:00:01", "Validation Time": "0:00:00"}, {"epoch": 81, "Training Loss": 0.05329537711777659, "Validation Loss": 0.1100162496721303, "Training Time": "0:00:01", "Validation Time": "0:00:00"}, {"epoch": 82, "Training Loss": 0.055772985959815426, "Validation Loss": 0.10989382055898507, "Training Time": "0:00:01", "Validation Time": "0:00:00"}, {"epoch": 83, "Training Loss": 0.052568942919200244, "Validation Loss": 0.11620093778603607, "Training Time": "0:00:01", "Validation Time": "0:00:00"}, {"epoch": 84, "Training Loss": 0.05617836281700536, "Validation Loss": 0.10428280928344638, "Training Time": "0:00:01", "Validation Time": "0:00:00"}, {"epoch": 85, "Training Loss": 0.052431240248992, "Validation Loss": 0.10117943833271663, "Training Time": "0:00:01", "Validation Time": "0:00:00"}, {"epoch": 86, "Training Loss": 0.05451707792316758, "Validation Loss": 0.12044919289096638, "Training Time": "0:00:01", "Validation Time": "0:00:00"}, {"epoch": 87, "Training Loss": 0.05221739770238136, "Validation Loss": 0.12160592940118578, "Training Time": "0:00:01", "Validation Time": "0:00:00"}, {"epoch": 88, "Training Loss": 0.052081282389198624, "Validation Loss": 0.11085641860134071, "Training Time": "0:00:01", "Validation Time": "0:00:00"}, {"epoch": 89, "Training Loss": 0.05606363376732482, "Validation Loss": 0.10624533539844884, "Training Time": "0:00:01", "Validation Time": "0:00:00"}, {"epoch": 90, "Training Loss": 0.04994903643897106, "Validation Loss": 0.10988544996965814, "Training Time": "0:00:01", "Validation Time": "0:00:00"}, {"epoch": 91, "Training Loss": 0.05214739768917477, "Validation Loss": 0.10726461635419617, "Training Time": "0:00:01", "Validation Time": "0:00:00"}, {"epoch": 92, "Training Loss": 0.05356328227817146, "Validation Loss": 0.12136802353240826, "Training Time": "0:00:01", "Validation Time": "0:00:00"}, {"epoch": 93, "Training Loss": 0.04947053938670907, "Validation Loss": 0.10889646362651277, "Training Time": "0:00:01", "Validation Time": "0:00:00"}, {"epoch": 94, "Training Loss": 0.05189779689752085, "Validation Loss": 0.11195164663648163, "Training Time": "0:00:01", "Validation Time": "0:00:00"}, {"epoch": 95, "Training Loss": 0.05186955649838891, "Validation Loss": 0.10663355976619103, "Training Time": "0:00:01", "Validation Time": "0:00:00"}, {"epoch": 96, "Training Loss": 0.049034900170599305, "Validation Loss": 0.10296091920247784, "Training Time": "0:00:01", "Validation Time": "0:00:00"}, {"epoch": 97, "Training Loss": 0.053046250057428385, "Validation Loss": 0.10069541081234261, "Training Time": "0:00:01", "Validation Time": "0:00:00"}, {"epoch": 98, "Training Loss": 0.05259875949732093, "Validation Loss": 0.10180564273010802, "Training Time": "0:00:01", "Validation Time": "0:00:00"}, {"epoch": 99, "Training Loss": 0.05505613147952529, "Validation Loss": 0.10384268292950259, "Training Time": "0:00:01", "Validation Time": "0:00:00"}, {"epoch": 100, "Training Loss": 0.050106788673546426, "Validation Loss": 0.10460011598964532, "Training Time": "0:00:01", "Validation Time": "0:00:00"}]